AUTHORS.md
CONTRIBUTING.md
LICENSE.txt
MANIFEST.in
README.md
setup.py
spyder_pomodoro_timer/__init__.py
spyder_pomodoro_timer.egg-info/PKG-INFO
spyder_pomodoro_timer.egg-info/SOURCES.txt
spyder_pomodoro_timer.egg-info/dependency_links.txt
spyder_pomodoro_timer.egg-info/entry_points.txt
spyder_pomodoro_timer.egg-info/requires.txt
spyder_pomodoro_timer.egg-info/top_level.txt
spyder_pomodoro_timer/spyder/__init__.py
spyder_pomodoro_timer/spyder/api.py
spyder_pomodoro_timer/spyder/config.py
spyder_pomodoro_timer/spyder/confpage.py
spyder_pomodoro_timer/spyder/container.py
spyder_pomodoro_timer/spyder/plugin.py
spyder_pomodoro_timer/spyder/widgets.py