Metadata-Version: 2.1
Name: spyder-pomodoro-timer
Version: 0.0.5.dev0
Summary: A very simple pomodoro timer that shows in the status bar.
Home-page: https://github.com/map0logo/spyder-pomodoro-timer
Author: Francisco Palm
Author-email: fpalm@qu4nt.com
License: MIT license
Platform: UNKNOWN
Classifier: Operating System :: MacOS
Classifier: Operating System :: Microsoft :: Windows
Classifier: Operating System :: POSIX :: Linux
Classifier: Programming Language :: Python :: 3
Classifier: Programming Language :: Python :: 3.7
Classifier: Programming Language :: Python :: 3.8
Classifier: Programming Language :: Python :: 3.9
Classifier: Development Status :: 3 - Alpha
Classifier: Intended Audience :: Education
Classifier: Intended Audience :: Science/Research
Classifier: Intended Audience :: Developers
Classifier: Intended Audience :: End Users/Desktop
Classifier: Topic :: Scientific/Engineering
Classifier: Topic :: Utilities
Requires-Python: >= 3.7
License-File: LICENSE.txt
License-File: AUTHORS.md
